turmachpy/__init__.py
turmachpy/binary_encoding.py
turmachpy/deep_neural_networks_tm.py
turmachpy/gpt_tm.py
turmachpy/grid_tape_tm.py
turmachpy/halt_decider.py
turmachpy/language_classifier.py
turmachpy/linear_layer.py
turmachpy/multi_tape_tm.py
turmachpy/non_deterministic_tm.py
turmachpy/single_tape_tm.py
turmachpy/universal_tm.py
turmachpy-0.1.2.dist-info/licenses/LICENSE
turmachpy-0.1.2.dist-info/METADATA
turmachpy-0.1.2.dist-info/WHEEL
turmachpy-0.1.2.dist-info/top_level.txt
turmachpy-0.1.2.dist-info/RECORD
