Metadata-Version: 2.4
Name: turmachpy
Version: 0.1.2
Summary: A lightweight package written for simulating a variety of Turing machines.
Author-email: Omar <omar.r.nawab@gmail.com>
License: MIT
Requires-Python: >=3.7
License-File: LICENSE
Requires-Dist: safetensors
Requires-Dist: tiktoken
Requires-Dist: numpy
Dynamic: license-file
